Workbook

Sheet fornecedores
A1: Período | B1: Fornecedor | C1: Último pagto ano | D1: CPF/CNPJ | E1: Valor Pago | F1: Coluna1 | G1: Coluna2
A2: 2025 | B2: A. C. R. AVALIACOES LTDA - ME | C2: 45880 | D2: 08.890.317/0001-52 | E2: 3920 | F2: =MONTH(C2) -> 8 | G2: =TEXT(F2*29, "mmmm") -> agosto
A3: 2025 | B3: A CASA DE EQUIPAMENTOS DO PORTAO AUTOMATICO LTDA ME | C3: 45736 | D3: 01.419.531/0001-86 | E3: 1010 | F3: =MONTH(C3) -> 3 | G3: =TEXT(F3*29, "mmmm") -> março
A4: 2025 | B4: A. DE A. PEREIRA LTDA | C4: 45922 | D4: 67.825.190/0001-57 | E4: 12759.87 | F4: =MONTH(C4) -> 9 | G4: =TEXT(F4*29, "mmmm") -> setembro
A5: 2025 | B5: A M COMERCIO DE MADEIRAS LTDA | C5: 45876 | D5: 49.836.542/0001-98 | E5: 1.34 | F5: =MONTH(C5) -> 8 | G5: =TEXT(F5*29, "mmmm") -> agosto
A6: 2025 | B6: A. M. PRESTACAO DE SERVICOS LTDA | C6: 45798 | D6: 18.347.265/0001-26 | E6: 720 | F6: =MONTH(C6) -> 5 | G6: =TEXT(F6*29, "mmmm") -> maio
A7: 2025 | B7: AAP CONSULT ENGENHARIA E REGULARIZAÇÕES LTDA | C7: 45931 | D7: 49.922.516/0001-82 | E7: 3960 | F7: =MONTH(C7) -> 10 | G7: =TEXT(F7*29, "mmmm") -> outubro
A8: 2025 | B8: AARON SALES DE ALMEIDA | C8: 45915 | D8: 316.068.668-00 | E8: 875.2 | F8: =MONTH(C8) -> 9 | G8: =TEXT(F8*29, "mmmm") -> setembro
A9: 2025 | B9: ABBOTT LABORATORIOS DO BRASIL LTDA | C9: 45960 | D9: 56.998.701/0033-01 | E9: 828208 | F9: =MONTH(C9) -> 10 | G9: =TEXT(F9*29, "mmmm") -> outubro
A10: 2025 | B10: ABBOTT LABORATORIOS DO BRASIL LTDA | C10: 45733 | D10: 56.998.701/0034-84 | E10: 1049.7 | F10: =MONTH(C10) -> 3 | G10: =TEXT(F10*29, "mmmm") -> março
A11: 2025 | B11: ABBVIE FARMACEUTICA LTDA. | C11: 45663 | D11: 15.800.545/0004-00 | E11: 17809.68 | F11: =MONTH(C11) -> 1 | G11: =TEXT(F11*29, "mmmm") -> janeiro
A12: 2025 | B12: ABC DO VALE TRANSPORTES LTDA | C12: 45803 | D12: 22.399.193/0001-38 | E12: 4360.5 | F12: =MONTH(C12) -> 5 | G12: =TEXT(F12*29, "mmmm") -> maio
A13: 2025 | B13: ABC TRANSPORTES COLETIVOS VALE PARAIBA LTDA | C13: 46009 | D13: 45.176.864/0001-05 | E13: 10161.4 | F13: =MONTH(C13) -> 12 | G13: =TEXT(F13*29, "mmmm") -> dezembro
... A8887: 2025 | B8887: 62.213.408 CARLOS EDUARDO RIBEIRO DOS SANTOS | C8887: 46007 | D8887: 62.213.408/0001-07 | E8887: 13600 | F8887: =MONTH(C8887) -> 12 | G8887: =TEXT(F8887*29, "mmmm") -> dezembro

Sheet Planilha4
A2: Total de pagamentos | B2: (Tudo)
A4: Rótulos de Linha | B4: Soma de Total de gastos
A5: Janeiro | B5: 20352123
A6: Fevereiro | B6: 4885960.9
A7: Março | B7: 14138912
A8: Abril | B8: 2582259.2
A9: Maio | B9: 11224910
A10: Junho | B10: 6453787.8
A11: Julho | B11: 6839808.2
A12: Agosto | B12: 83590695
A13: Setembro | B13: 4763691
A14: Outubro | B14: 18233017
A15: Novembro | B15: 63208008
A16: Dezembro | B16: 2.9237187e+09
A17: Total Geral | B17: 3.1599918e+09

Sheet Planilha1
A1: Mês (2025) | B1: Total de gastos | C1: Total de pagamentos
A2: Janeiro | B2: =SUMIF(fornecedores!G:G,Planilha1!A2,Tabela2[[#Headers],[Valor Pago]]) -> 20352123 | C2: =COUNTIF(fornecedores!G:G, Planilha1!A2) -> 291
A3: Fevereiro | B3: =SUMIF(fornecedores!G:G,Planilha1!A3,Tabela2[[#Headers],[Valor Pago]]) -> 4885960.9 | C3: =COUNTIF(fornecedores!G:G, Planilha1!A3) -> 680
A4: Março | B4: =SUMIF(fornecedores!G:G,Planilha1!A4,Tabela2[[#Headers],[Valor Pago]]) -> 14138912 | C4: =COUNTIF(fornecedores!G:G, Planilha1!A4) -> 345
A5: Abril | B5: =SUMIF(fornecedores!G:G,Planilha1!A5,Tabela2[[#Headers],[Valor Pago]]) -> 2582259.2 | C5: =COUNTIF(fornecedores!G:G, Planilha1!A5) -> 281
A6: Maio | B6: =SUMIF(fornecedores!G:G,Planilha1!A6,Tabela2[[#Headers],[Valor Pago]]) -> 11224910 | C6: =COUNTIF(fornecedores!G:G, Planilha1!A6) -> 352
A7: Junho | B7: =SUMIF(fornecedores!G:G,Planilha1!A7,Tabela2[[#Headers],[Valor Pago]]) -> 6453787.8 | C7: =COUNTIF(fornecedores!G:G, Planilha1!A7) -> 386
A8: Julho | B8: =SUMIF(fornecedores!G:G,Planilha1!A8,Tabela2[[#Headers],[Valor Pago]]) -> 6839808.2 | C8: =COUNTIF(fornecedores!G:G, Planilha1!A8) -> 405
A9: Agosto | B9: =SUMIF(fornecedores!G:G,Planilha1!A9,Tabela2[[#Headers],[Valor Pago]]) -> 83590695 | C9: =COUNTIF(fornecedores!G:G, Planilha1!A9) -> 415
A10: Setembro | B10: =SUMIF(fornecedores!G:G,Planilha1!A10,Tabela2[[#Headers],[Valor Pago]]) -> 4763691 | C10: =COUNTIF(fornecedores!G:G, Planilha1!A10) -> 428
A11: Outubro | B11: =SUMIF(fornecedores!G:G,Planilha1!A11,Tabela2[[#Headers],[Valor Pago]]) -> 18233017 | C11: =COUNTIF(fornecedores!G:G, Planilha1!A11) -> 496
A12: Novembro | B12: =SUMIF(fornecedores!G:G,Planilha1!A12,Tabela2[[#Headers],[Valor Pago]]) -> 63208008 | C12: =COUNTIF(fornecedores!G:G, Planilha1!A12) -> 1127
A13: Dezembro | B13: =SUMIF(fornecedores!G:G,Planilha1!A13,Tabela2[[#Headers],[Valor Pago]]) -> 2.9237187e+09 | C13: =COUNTIF(fornecedores!G:G, Planilha1!A13) -> 3680
